pystages/__init__.py
pystages/autofocus.py
pystages/cncrouter.py
pystages/corvus.py
pystages/exceptions.py
pystages/grbl.py
pystages/m3fs.py
pystages/pi.py
pystages/pi_errors.py
pystages/smc100.py
pystages/stage.py
pystages/tic.py
pystages/vector.py
pystages/gui/__init__.py
pystages/gui/__main__.py
pystages/gui/gui.py
pystages/gui/util.py
pystages-1.3.dist-info/METADATA
pystages-1.3.dist-info/WHEEL
pystages-1.3.dist-info/licenses/COPYING
pystages-1.3.dist-info/licenses/COPYING.LESSER
pystages-1.3.dist-info/RECORD
