Metadata-Version: 2.4
Name: pystages
Version: 1.3
Summary: Motorized stage control library for scientific applications
Project-URL: Homepage, https://github.com/Ledger-Donjon/pystages
Project-URL: Bug Tracker, https://github.com/Ledger-Donjon/pystages/issues
Project-URL: Documentation, https://pystages.readthedocs.io/en/latest
Author-email: Olivier Hérivaux <olivier.heriveaux@ledger.fr>, Michaël Mouchous <michael.mouchous@ledger.fr>
License-File: COPYING
License-File: COPYING.LESSER
Classifier: License :: OSI Approved :: GNU Lesser General Public License v3 (LGPLv3)
Classifier: Operating System :: OS Independent
Classifier: Programming Language :: Python :: 3
Requires-Python: >=3.9
Requires-Dist: numpy
Requires-Dist: pyqt6
Requires-Dist: pyserial
Requires-Dist: pyusb
